robust_serial/__init__.py
robust_serial/robust_serial.py
robust_serial/threads.py
robust_serial/utils.py
robust_serial-0.2.dist-info/LICENSE
robust_serial-0.2.dist-info/METADATA
robust_serial-0.2.dist-info/WHEEL
robust_serial-0.2.dist-info/top_level.txt
robust_serial-0.2.dist-info/RECORD
