Metadata-Version: 2.1
Name: robust-serial
Version: 0.2
Summary: Simple and Robust Serial Communication Protocol
Home-page: https://github.com/araffin/arduino-robust-serial
Author: Antonin RAFFIN
Author-email: antonin.raffin@ensta.org
License: MIT
Keywords: serial hardware arduino RS232 communication protocol raspberry
Classifier: Programming Language :: Python :: 3
Classifier: Programming Language :: Python :: 3.8
Classifier: Programming Language :: Python :: 3.9
Classifier: Programming Language :: Python :: 3.10
Requires-Python: >=3.8
License-File: LICENSE
Requires-Dist: pyserial
Provides-Extra: docs
Requires-Dist: sphinx ; extra == 'docs'
Requires-Dist: sphinx-rtd-theme ; extra == 'docs'
Requires-Dist: sphinx-autodoc-typehints ; extra == 'docs'
Provides-Extra: tests
Requires-Dist: pytest ; extra == 'tests'
Requires-Dist: pytest-cov ; extra == 'tests'
Requires-Dist: mypy ; extra == 'tests'
Requires-Dist: ruff ; extra == 'tests'
Requires-Dist: black ; extra == 'tests'
Requires-Dist: isort ; extra == 'tests'
